jupyterlab_pdf_preview/__init__.py
jupyterlab_pdf_preview-0.2.1.data/data/share/jupyter/labextensions/jupyterlab-pdf-preview/package.json
jupyterlab_pdf_preview-0.2.1.data/data/share/jupyter/labextensions/jupyterlab-pdf-preview/static/050229fd2a4f7514cd1e.mjs
jupyterlab_pdf_preview-0.2.1.data/data/share/jupyter/labextensions/jupyterlab-pdf-preview/static/050229fd2a4f7514cd1e.mjs.LICENSE.txt
jupyterlab_pdf_preview-0.2.1.data/data/share/jupyter/labextensions/jupyterlab-pdf-preview/static/279.138dcfb4965516914763.js
jupyterlab_pdf_preview-0.2.1.data/data/share/jupyter/labextensions/jupyterlab-pdf-preview/static/279.138dcfb4965516914763.js.LICENSE.txt
jupyterlab_pdf_preview-0.2.1.data/data/share/jupyter/labextensions/jupyterlab-pdf-preview/static/369.8a93a506f3159d78e080.js
jupyterlab_pdf_preview-0.2.1.data/data/share/jupyter/labextensions/jupyterlab-pdf-preview/static/369.8a93a506f3159d78e080.js.LICENSE.txt
jupyterlab_pdf_preview-0.2.1.data/data/share/jupyter/labextensions/jupyterlab-pdf-preview/static/848.a5979aa8836740a31a4a.js
jupyterlab_pdf_preview-0.2.1.data/data/share/jupyter/labextensions/jupyterlab-pdf-preview/static/848.a5979aa8836740a31a4a.js.LICENSE.txt
jupyterlab_pdf_preview-0.2.1.data/data/share/jupyter/labextensions/jupyterlab-pdf-preview/static/remoteEntry.0b592562f6baa86caeeb.js
jupyterlab_pdf_preview-0.2.1.data/data/share/jupyter/labextensions/jupyterlab-pdf-preview/static/style.js
jupyterlab_pdf_preview-0.2.1.data/data/share/jupyter/labextensions/jupyterlab-pdf-preview/static/third-party-licenses.json
jupyterlab_pdf_preview-0.2.1.data/data/share/jupyter/labextensions/jupyterlab-pdf-preview/install.json
jupyterlab_pdf_preview-0.2.1.dist-info/METADATA
jupyterlab_pdf_preview-0.2.1.dist-info/WHEEL
jupyterlab_pdf_preview-0.2.1.dist-info/licenses/LICENSE
jupyterlab_pdf_preview-0.2.1.dist-info/RECORD
