Metadata-Version: 2.3
Name: jupyterlab-pdf-preview
Version: 0.2.1
Dynamic: Author
Dynamic: Author-email
Summary: JupyterLab extension to preview PDF files in the file browser on hover.
Project-URL: Homepage, https://github.com/PainterQubits/jupyterlab-pdf-preview
Project-URL: Repository, https://github.com/PainterQubits/jupyterlab-pdf-preview
License: BSD 3-Clause License
License-File: LICENSE
Keywords: jupyter,jupyterlab,jupyterlab-extension
Classifier: Framework :: Jupyter
Classifier: Framework :: Jupyter :: JupyterLab
Classifier: Framework :: Jupyter :: JupyterLab :: 4
Classifier: Framework :: Jupyter :: JupyterLab :: Extensions
Classifier: Framework :: Jupyter :: JupyterLab :: Extensions :: Prebuilt
Classifier: License :: OSI Approved :: BSD License
Classifier: Programming Language :: Python
Classifier: Programming Language :: Python :: 3
Classifier: Programming Language :: Python :: 3.9
Classifier: Programming Language :: Python :: 3.10
Classifier: Programming Language :: Python :: 3.11
Classifier: Programming Language :: Python :: 3.12
Requires-Python: >=3.9
